<?xml version = "1.0" encoding="Windows-1252" standalone="yes"?>
<GEOSuedi>
<progettisti>
<codice>1</codice>
<cognome>PIGNATA</cognome>
<nome>GIANNI</nome>
<qualifica></qualifica>
<codfiscale>PGNGNN70R27I138M</codfiscale>
<citta>SANREMO</citta>
<indirizzo>Via Martiri della Libertà, 458</indirizzo>
<cap>18038</cap>
<provincia>IM</provincia>
</progettisti>
<progettisti>
<codice>2</codice>
<cognome>GAZZANO</cognome>
<nome>GAZZANO SILVIA</nome>
<qualifica></qualifica>
<codfiscale>GZZSLV68D48E290W</codfiscale>
<citta>CIVEZZA</citta>
<indirizzo>Via Dante 15a</indirizzo>
<cap>18017</cap>
<provincia>IM</provincia>
</progettisti>
<progettisti>
<codice>4</codice>
<cognome>AMMIRATI</cognome>
<nome>ALBERTO</nome>
<qualifica></qualifica>
<codfiscale>MMRLRT58E31I138J</codfiscale>
<citta>CIPRESSA</citta>
<indirizzo>VIA FOSSATI, 25</indirizzo>
<cap>18017</cap>
<provincia>IM</provincia>
</progettisti>
<progettisti>
<codice>6</codice>
<cognome>DAMELE</cognome>
<nome>ANTONIO</nome>
<qualifica></qualifica>
<codfiscale>DMLNTN49H16H345P</codfiscale>
<citta>RIVA LIGURE</citta>
<indirizzo>VIA NINO BIXIO 52</indirizzo>
<cap>18015</cap>
<provincia>IM</provincia>
</progettisti>
<progettisti>
<codice>7</codice>
<cognome>DAMELE</cognome>
<nome>ANTONIO</nome>
<qualifica></qualifica>
<codfiscale>DMLNTN49H16H345P</codfiscale>
<citta>RIVA LIGURE</citta>
<indirizzo>VIA NINO BIXIO 52</indirizzo>
<cap>18015</cap>
<provincia>IM</provincia>
</progettisti>
<progettisti>
<codice>8</codice>
<cognome>DAMELE</cognome>
<nome>ANTONIO</nome>
<qualifica></qualifica>
<codfiscale>DMLNTN49H16H345P</codfiscale>
<citta>RIVA LIGURE</citta>
<indirizzo>VIA NINO BIXIO 52</indirizzo>
<cap>18015</cap>
<provincia>IM</provincia>
</progettisti>
<progettisti>
<codice>9</codice>
<cognome>CRESPI</cognome>
<nome>ANTONELLO</nome>
<qualifica></qualifica>
<codfiscale>CRSNNL88H10D969T</codfiscale>
<citta>CERIANA</citta>
<indirizzo>via mora 23</indirizzo>
<cap>18034</cap>
<provincia>IM</provincia>
</progettisti>
<progettisti>
<codice>10</codice>
<cognome>ROGGERI</cognome>
<nome>MARCO</nome>
<qualifica></qualifica>
<codfiscale>RGGMRC69S07I138E</codfiscale>
<citta>SANTO STEFANO AL MARE</citta>
<indirizzo>via Cardinal Meglia 28</indirizzo>
<cap>18010</cap>
<provincia>IM</provincia>
</progettisti>
<progettisti>
<codice>11</codice>
<cognome>MEROGNO</cognome>
<nome>DANILO</nome>
<qualifica></qualifica>
<codfiscale>MRGDNL73E25I138C</codfiscale>
<citta>TAGGIA</citta>
<indirizzo>VIA C.COLOMBO 52</indirizzo>
<cap>18018</cap>
<provincia>IM</provincia>
</progettisti>
<progettisti>
<codice>12</codice>
<cognome>DAMELE</cognome>
<nome>ANTONIO</nome>
<qualifica></qualifica>
<codfiscale>DMLNTN49H16H345P</codfiscale>
<citta>RIVA LIGURE</citta>
<indirizzo>VIA NINO BIXIO 52</indirizzo>
<cap>18015</cap>
<provincia>IM</provincia>
</progettisti>
<progettisti>
<codice>13</codice>
<cognome>CARLETTI</cognome>
<nome>MAURIZIO</nome>
<qualifica></qualifica>
<codfiscale>CRLMRZ61R07I138M</codfiscale>
<citta>ARMA DI TAGGIA</citta>
<indirizzo>via nino pesce 3, localita` Arma di Taggia</indirizzo>
<cap>18018</cap>
<provincia>IM</provincia>
</progettisti>
<progettisti>
<codice>14</codice>
<cognome>PERRONE</cognome>
<nome>SIMONE</nome>
<qualifica></qualifica>
<codfiscale>PRRSMN83D21I138I</codfiscale>
<citta>SANREMO</citta>
<indirizzo>VIA ZEFFIRO MASSA 289</indirizzo>
<cap>18038</cap>
<provincia>IM</provincia>
</progettisti>
<progettisti>
<codice>15</codice>
<cognome>VENTURI</cognome>
<nome>ALEX</nome>
<qualifica></qualifica>
<codfiscale>VNTLXA90C21G999C</codfiscale>
<citta>TAGGIA</citta>
<indirizzo>VIA II TRAVERSA DELLA CORNICE 31</indirizzo>
<cap>18018</cap>
<provincia>IM</provincia>
</progettisti>
<progettisti>
<codice>16</codice>
<cognome>DE BENEDETTO</cognome>
<nome>IVAN</nome>
<qualifica></qualifica>
<codfiscale>DBNVNI81B17I138P</codfiscale>
<citta>SANREMO</citta>
<indirizzo>Via G. Matteotti 134</indirizzo>
<cap>18038</cap>
<provincia>IM</provincia>
</progettisti>
<progettisti>
<codice>17</codice>
<cognome>REBAUDO</cognome>
<nome>IVANO</nome>
<qualifica></qualifica>
<codfiscale>RBDVNI58P27E290X</codfiscale>
<citta>SANTO STEFANO AL MARE</citta>
<indirizzo>VIA ROMA 28</indirizzo>
<cap>18010</cap>
<provincia>IM</provincia>
</progettisti>
<progettisti>
<codice>18</codice>
<cognome>REBAUDO</cognome>
<nome>IVANO</nome>
<qualifica></qualifica>
<codfiscale>RBDVNI58P27E290X</codfiscale>
<citta>SANTO STEFANO AL MARE</citta>
<indirizzo>VIA ROMA 28</indirizzo>
<cap>18010</cap>
<provincia>IM</provincia>
</progettisti>
<progettisti>
<codice>19</codice>
<cognome>MASSA</cognome>
<nome>DAVIDE</nome>
<qualifica></qualifica>
<codfiscale>MSSDVD71C07C722A</codfiscale>
<citta>TORINO</citta>
<indirizzo>PIAZZALE MONASTERO, 13</indirizzo>
<cap>10146</cap>
<provincia>TO</provincia>
</progettisti>
<progettisti>
<codice>20</codice>
<cognome>SAPPA</cognome>
<nome>VALENTINO</nome>
<qualifica></qualifica>
<codfiscale>SPPVNT87H04E290F</codfiscale>
<citta>SANREMO</citta>
<indirizzo>VIA DANTE ALIGHIERI 56</indirizzo>
<cap>18038</cap>
<provincia>IM</provincia>
</progettisti>
<progettisti>
<codice>21</codice>
<cognome>SAPPA</cognome>
<nome>VALENTINO</nome>
<qualifica></qualifica>
<codfiscale>SPPVNT87H04E290F</codfiscale>
<citta>SANREMO</citta>
<indirizzo>VIA DANTE ALIGHIERI 56</indirizzo>
<cap>18038</cap>
<provincia>IM</provincia>
</progettisti>
<progettisti>
<codice>22</codice>
<cognome>SCAGLIONE</cognome>
<nome>ANDREA</nome>
<qualifica></qualifica>
<codfiscale>SCGNDR73E06B594M</codfiscale>
<citta>ALBA</citta>
<indirizzo>corso piave 4</indirizzo>
<cap>12051</cap>
<provincia>CN</provincia>
</progettisti>
<progettisti>
<codice>23</codice>
<cognome>DAMELE</cognome>
<nome>ANTONIO</nome>
<qualifica></qualifica>
<codfiscale>DMLNTN49H16H345P</codfiscale>
<citta>RIVA LIGURE</citta>
<indirizzo>VIA NINO BIXIO 52</indirizzo>
<cap>18015</cap>
<provincia>IM</provincia>
</progettisti>
<progettisti>
<codice>24</codice>
<cognome>ROGGERI</cognome>
<nome>MARCO</nome>
<qualifica></qualifica>
<codfiscale>RGGMRC69S07I138E</codfiscale>
<citta>SANTO STEFANO AL MARE</citta>
<indirizzo>via Cardinal Meglia 28</indirizzo>
<cap>18010</cap>
<provincia>IM</provincia>
</progettisti>
<progettisti>
<codice>25</codice>
<cognome>VIERO</cognome>
<nome>ROBERTA</nome>
<qualifica></qualifica>
<codfiscale>VRIRRT63H47I138U</codfiscale>
<citta>SANREMO</citta>
<indirizzo>via Roma, 104</indirizzo>
<cap>18038</cap>
<provincia>IM</provincia>
</progettisti>
<progettisti>
<codice>26</codice>
<cognome>FESTA</cognome>
<nome>DANIELE</nome>
<qualifica></qualifica>
<codfiscale>FSTDNL82R18I138C</codfiscale>
<citta>TAGGIA</citta>
<indirizzo>Via Paolo Boselli, 19</indirizzo>
<cap>18018</cap>
<provincia>IM</provincia>
</progettisti>
<progettisti>
<codice>27</codice>
<cognome>URBINI</cognome>
<nome>ALESSIO</nome>
<qualifica></qualifica>
<codfiscale>RBNLSS84P12I138C</codfiscale>
<citta>SANREMO</citta>
<indirizzo>VIA FERALDI 26</indirizzo>
<cap>18038</cap>
<provincia>IM</provincia>
</progettisti>
<progettisti>
<codice>28</codice>
<cognome>GARIBALDI</cognome>
<nome>DIEGO</nome>
<qualifica></qualifica>
<codfiscale>GRBDGI98L11I138S</codfiscale>
<citta>RIVA LIGURE</citta>
<indirizzo>via aurelia 14/E</indirizzo>
<cap>18015</cap>
<provincia>IM</provincia>
</progettisti>
<progettisti>
<codice>29</codice>
<cognome>ALAURIA</cognome>
<nome>SIMONA</nome>
<qualifica></qualifica>
<codfiscale>LRASMN75C50L219M</codfiscale>
<citta>OSPEDALETTI</citta>
<indirizzo>CORSO REGINA MARGHERITA 13</indirizzo>
<cap>18014</cap>
<provincia>IM</provincia>
</progettisti>
<progettisti>
<codice>30</codice>
<cognome>ALAURIA</cognome>
<nome>SIMONA</nome>
<qualifica></qualifica>
<codfiscale>LRASMN75C50L219M</codfiscale>
<citta>OSPEDALETTI</citta>
<indirizzo>CORSO REGINA MARGHERITA 13</indirizzo>
<cap>18014</cap>
<provincia>IM</provincia>
</progettisti>
<progettisti>
<codice>31</codice>
<cognome>CONIO</cognome>
<nome>MARIO</nome>
<qualifica></qualifica>
<codfiscale>CNOMRA71P24I138H</codfiscale>
<citta>TAGGIA</citta>
<indirizzo>VIA L. ARGENTINA N° 23</indirizzo>
<cap>18018</cap>
<provincia>IM</provincia>
</progettisti>
<progettisti>
<codice>32</codice>
<cognome>DAMELE</cognome>
<nome>ANTONIO</nome>
<qualifica></qualifica>
<codfiscale>DMLNTN49H16H345P</codfiscale>
<citta>RIVA LIGURE</citta>
<indirizzo>VIA NINO BIXIO 52</indirizzo>
<cap>18015</cap>
<provincia>IM</provincia>
</progettisti>
<progettisti>
<codice>33</codice>
<cognome>REBAUDO</cognome>
<nome>MATTIA</nome>
<qualifica></qualifica>
<codfiscale>RBDMTT84B28E290U</codfiscale>
<citta>POMPEIANA</citta>
<indirizzo>VIA CAVOUR 51</indirizzo>
<cap>18015</cap>
<provincia>IM</provincia>
</progettisti>
<progettisti>
<codice>34</codice>
<cognome>DAMELE</cognome>
<nome>ANTONIO</nome>
<qualifica></qualifica>
<codfiscale>DMLNTN49H16H345P</codfiscale>
<citta>RIVA LIGURE</citta>
<indirizzo>VIA NINO BIXIO 52</indirizzo>
<cap>18015</cap>
<provincia>IM</provincia>
</progettisti>
<progettisti>
<codice>35</codice>
<cognome>ABBÀ</cognome>
<nome>ALESSANDRO</nome>
<qualifica></qualifica>
<codfiscale>BBALSN74C17L219Q</codfiscale>
<citta>PINEROLO</citta>
<indirizzo>VIA TABONA 5/A C/O STUDIO74 SRL</indirizzo>
<cap>10064</cap>
<provincia>TO</provincia>
</progettisti>
<progettisti>
<codice>36</codice>
<cognome>MERANO</cognome>
<nome>ANNACLETA</nome>
<qualifica></qualifica>
<codfiscale>MRNNCL53C67B020D</codfiscale>
<citta>TAGGIA</citta>
<indirizzo>TRAVERSA DI VIA CASTELLETTI, 33/1</indirizzo>
<cap>18018</cap>
<provincia>IM</provincia>
</progettisti>
<progettisti>
<codice>37</codice>
<cognome>ABBÀ</cognome>
<nome>ALESSANDRO</nome>
<qualifica></qualifica>
<codfiscale>BBALSN74C17L219Q</codfiscale>
<citta>PINEROLO</citta>
<indirizzo>VIA TABONA 5/A C/O STUDIO74 SRL</indirizzo>
<cap>10064</cap>
<provincia>TO</provincia>
</progettisti>
<progettisti>
<codice>38</codice>
<cognome>DAMELE</cognome>
<nome>ANTONIO</nome>
<qualifica></qualifica>
<codfiscale>DMLNTN49H16H345P</codfiscale>
<citta>RIVA LIGURE</citta>
<indirizzo>VIA NINO BIXIO 52</indirizzo>
<cap>18015</cap>
<provincia>IM</provincia>
</progettisti>
<progettisti>
<codice>39</codice>
<cognome>SICCARDI</cognome>
<nome>ROBERTO</nome>
<qualifica></qualifica>
<codfiscale>SCCRRT70S23I138B</codfiscale>
<citta>TAGGIA</citta>
<indirizzo>VIA ANDREA DORIA 32</indirizzo>
<cap>18018</cap>
<provincia>IM</provincia>
</progettisti>
<progettisti>
<codice>40</codice>
<cognome>RIVOIRA</cognome>
<nome>PAOLO</nome>
<qualifica></qualifica>
<codfiscale>RVRPLA74R02E290F</codfiscale>
<citta>IMPERIA</citta>
<indirizzo>VIA FELICE PAGLIERI 46</indirizzo>
<cap>18100</cap>
<provincia>IM</provincia>
</progettisti>
<progettisti>
<codice>41</codice>
<cognome>MOLINARI</cognome>
<nome>MARCO</nome>
<qualifica></qualifica>
<codfiscale>MLNMRC67B15D969C</codfiscale>
<citta>IMPERIA</citta>
<indirizzo>Via Tommaso Schiva 48</indirizzo>
<cap>18100</cap>
<provincia>IM</provincia>
</progettisti>
<progettisti>
<codice>42</codice>
<cognome>ANSELMA</cognome>
<nome>ROMANA</nome>
<qualifica></qualifica>
<codfiscale>NSLRMN72B45L219I</codfiscale>
<citta>LA MORRA</citta>
<indirizzo>via garibaldi 23</indirizzo>
<cap>12064</cap>
<provincia>CN</provincia>
</progettisti>
<progettisti>
<codice>43</codice>
<cognome>TAGLIATINI</cognome>
<nome>ALBERTO</nome>
<qualifica></qualifica>
<codfiscale>TGLLRT77M02I138J</codfiscale>
<citta>TAGGIA</citta>
<indirizzo>via della cornice 78</indirizzo>
<cap>18018</cap>
<provincia>IM</provincia>
</progettisti>
<progettisti>
<codice>44</codice>
<cognome>DE ANDREIS</cognome>
<nome>GIANFRANCO</nome>
<qualifica></qualifica>
<codfiscale>DNDGFR63A25I138X</codfiscale>
<citta>SANREMO</citta>
<indirizzo>Via Pietro Calvi n.1</indirizzo>
<cap>18038</cap>
<provincia>IM</provincia>
</progettisti>
<progettisti>
<codice>45</codice>
<cognome>DAMELE</cognome>
<nome>ANTONIO</nome>
<qualifica></qualifica>
<codfiscale>DMLNTN49H16H345P</codfiscale>
<citta>RIVA LIGURE</citta>
<indirizzo>VIA NINO BIXIO 52</indirizzo>
<cap>18015</cap>
<provincia>IM</provincia>
</progettisti>
<progettisti>
<codice>46</codice>
<cognome>SECONDO</cognome>
<nome>DIMITRI</nome>
<qualifica></qualifica>
<codfiscale>SCNDTR71M29I138B</codfiscale>
<citta>TAGGIA</citta>
<indirizzo>via Boselli 19</indirizzo>
<cap>18018</cap>
<provincia>IM</provincia>
</progettisti>
<progettisti>
<codice>47</codice>
<cognome>MASSA</cognome>
<nome>STEFANO</nome>
<qualifica></qualifica>
<codfiscale>MSSSFN96T07I138Y</codfiscale>
<citta>SANREMO</citta>
<indirizzo>VIA MARTIRI DELLA LIBERTA' 226</indirizzo>
<cap>18038</cap>
<provincia>IM</provincia>
</progettisti>
<progettisti>
<codice>48</codice>
<cognome>MAIONE</cognome>
<nome>ALESSANDRO</nome>
<qualifica></qualifica>
<codfiscale>MNALSN81T28F839P</codfiscale>
<citta>GIUGLIANO IN CAMPANIA</citta>
<indirizzo>VIA VICINALE PALAZZOLE 13</indirizzo>
<cap>80014</cap>
<provincia>NA</provincia>
</progettisti>
<progettisti>
<codice>49</codice>
<cognome>BERTANI</cognome>
<nome>FABIO</nome>
<qualifica></qualifica>
<codfiscale>BRTFBA71C30E290E</codfiscale>
<citta>TAGGIA</citta>
<indirizzo>VIA DEL FORNO 2</indirizzo>
<cap>18018</cap>
<provincia>IM</provincia>
</progettisti>
<progettisti>
<codice>50</codice>
<cognome>RAIMONDO</cognome>
<nome>SERGIO</nome>
<qualifica></qualifica>
<codfiscale>RMNSRG65M13I138S</codfiscale>
<citta>TAGGIA</citta>
<indirizzo>VIA DELLA STAZIONE, 32</indirizzo>
<cap>180</cap>
<provincia>IM</provincia>
</progettisti>
<progettisti>
<codice>51</codice>
<cognome>RAIMONDO</cognome>
<nome>SERGIO</nome>
<qualifica></qualifica>
<codfiscale>RMNSRG65M13I138S</codfiscale>
<citta>TAGGIA</citta>
<indirizzo>VIA DELLA STAZIONE, 32</indirizzo>
<cap>180</cap>
<provincia>IM</provincia>
</progettisti>
<progettisti>
<codice>52</codice>
<cognome>GARIBALDI</cognome>
<nome>DIEGO</nome>
<qualifica></qualifica>
<codfiscale>GRBDGI98L11I138S</codfiscale>
<citta>RIVA LIGURE</citta>
<indirizzo>via aurelia 14/E</indirizzo>
<cap>18015</cap>
<provincia>IM</provincia>
</progettisti>
<progettisti>
<codice>53</codice>
<cognome>RAIMONDO</cognome>
<nome>SERGIO</nome>
<qualifica></qualifica>
<codfiscale>RMNSRG65M13I138S</codfiscale>
<citta>TAGGIA</citta>
<indirizzo>VIA DELLA STAZIONE, 32</indirizzo>
<cap>180</cap>
<provincia>IM</provincia>
</progettisti>
<progettisti>
<codice>54</codice>
<cognome>REBAUDO</cognome>
<nome>MATTIA</nome>
<qualifica></qualifica>
<codfiscale>RBDMTT84B28E290U</codfiscale>
<citta>POMPEIANA</citta>
<indirizzo>VIA CAVOUR 51</indirizzo>
<cap>18015</cap>
<provincia>IM</provincia>
</progettisti>
<progettisti>
<codice>56</codice>
<cognome>DAMELE</cognome>
<nome>ANTONIO</nome>
<qualifica></qualifica>
<codfiscale>DMLNTN49H16H345P</codfiscale>
<citta>RIVA LIGURE</citta>
<indirizzo>VIA NINO BIXIO 52</indirizzo>
<cap>18015</cap>
<provincia>IM</provincia>
</progettisti>
<progettisti>
<codice>57</codice>
<cognome>MAMMONE</cognome>
<nome>ALESSANDRO</nome>
<qualifica></qualifica>
<codfiscale>MMMLSN75P22A984Y</codfiscale>
<citta>DOLCEACQUA</citta>
<indirizzo>VICOLO Cassini 1c</indirizzo>
<cap>18035</cap>
<provincia>IM</provincia>
</progettisti>
<progettisti>
<codice>58</codice>
<cognome>CONIO</cognome>
<nome>MARIO</nome>
<qualifica></qualifica>
<codfiscale>CNOMRA71P24I138H</codfiscale>
<citta>TAGGIA</citta>
<indirizzo>VIA L. ARGENTINA N° 23</indirizzo>
<cap>18018</cap>
<provincia>IM</provincia>
</progettisti>
<progettisti>
<codice>59</codice>
<cognome>DAMELE</cognome>
<nome>ANTONIO</nome>
<qualifica></qualifica>
<codfiscale>DMLNTN49H16H345P</codfiscale>
<citta>RIVA LIGURE</citta>
<indirizzo>VIA NINO BIXIO 52</indirizzo>
<cap>18015</cap>
<provincia>IM</provincia>
</progettisti>
<progettisti>
<codice>60</codice>
<cognome>CALVI</cognome>
<nome>MARCO</nome>
<qualifica></qualifica>
<codfiscale>CLVMRC68B03I138E</codfiscale>
<citta>SANREMO</citta>
<indirizzo>CORSO ORAZIO RAIMONDO 117</indirizzo>
<cap>18038</cap>
<provincia>IM</provincia>
</progettisti>
<progettisti>
<codice>61</codice>
<cognome>BOLOGNA</cognome>
<nome>RAFFAELLA</nome>
<qualifica></qualifica>
<codfiscale>BLGRFL73D56G388Y</codfiscale>
<citta>PAVIA</citta>
<indirizzo>VIA SONDRIO, 18</indirizzo>
<cap>18038</cap>
<provincia>PV</provincia>
</progettisti>
<progettisti>
<codice>62</codice>
<cognome>ROGGERI</cognome>
<nome>MARCO</nome>
<qualifica></qualifica>
<codfiscale>RGGMRC69S07I138E</codfiscale>
<citta>SANTO STEFANO AL MARE</citta>
<indirizzo>via Cardinal Meglia 28</indirizzo>
<cap>18010</cap>
<provincia>IM</provincia>
</progettisti>
<progettisti>
<codice>63</codice>
<cognome>GARZO</cognome>
<nome>MARCO</nome>
<qualifica></qualifica>
<codfiscale>GRZMRC61H08I138D</codfiscale>
<citta>TAGGIA</citta>
<indirizzo>VIA CORNICE CIV.73</indirizzo>
<cap>18018</cap>
<provincia>IM</provincia>
</progettisti>
<progettisti>
<codice>64</codice>
<cognome>FRASCAROLO</cognome>
<nome>ANDREA</nome>
<qualifica></qualifica>
<codfiscale>FRSNDR82M27L219T</codfiscale>
<citta>TORINO</citta>
<indirizzo>PIAZZA GRAN MADRE 3</indirizzo>
<cap>10131</cap>
<provincia>TO</provincia>
</progettisti>
<progettisti>
<codice>65</codice>
<cognome>ALBERTI</cognome>
<nome>CRISTIAN</nome>
<qualifica></qualifica>
<codfiscale>LBRCST81H22I138Q</codfiscale>
<citta>SANREMO</citta>
<indirizzo>CORSO GARIBALDI 189</indirizzo>
<cap>18038</cap>
<provincia>IM</provincia>
</progettisti>
<progettisti>
<codice>66</codice>
<cognome>PRATTICO'</cognome>
<nome>ALESSIO</nome>
<qualifica></qualifica>
<codfiscale>PRTLSS85T23A145J</codfiscale>
<citta>TAGGIA</citta>
<indirizzo>via san Francesco, 451</indirizzo>
<cap>1018</cap>
<provincia>IM</provincia>
</progettisti>
<progettisti>
<codice>67</codice>
<cognome>RODRIGUEZ</cognome>
<nome>ROBERTO</nome>
<qualifica></qualifica>
<codfiscale>RDRRRT63H28H501J</codfiscale>
<citta>OSPEDALETTI</citta>
<indirizzo>VIA GIACOMO MATTEOTTI 18</indirizzo>
<cap>18014</cap>
<provincia>IM</provincia>
</progettisti>
<progettisti>
<codice>68</codice>
<cognome>ROGGERI</cognome>
<nome>MARCO</nome>
<qualifica></qualifica>
<codfiscale>RGGMRC69S07I138E</codfiscale>
<citta>SANTO STEFANO AL MARE</citta>
<indirizzo>via Cardinal Meglia 28</indirizzo>
<cap>18010</cap>
<provincia>IM</provincia>
</progettisti>
<progettisti>
<codice>69</codice>
<cognome>SICCARDI</cognome>
<nome>ROBERTO</nome>
<qualifica></qualifica>
<codfiscale>SCCRRT70S23I138B</codfiscale>
<citta>TAGGIA</citta>
<indirizzo>VIA ANDREA DORIA 32</indirizzo>
<cap>18018</cap>
<provincia>IM</provincia>
</progettisti>
<progettisti>
<codice>70</codice>
<cognome>SICCARDI</cognome>
<nome>ROBERTO</nome>
<qualifica></qualifica>
<codfiscale>SCCRRT70S23I138B</codfiscale>
<citta>TAGGIA</citta>
<indirizzo>VIA ANDREA DORIA 32</indirizzo>
<cap>18018</cap>
<provincia>IM</provincia>
</progettisti>
<progettisti>
<codice>71</codice>
<cognome>ARTIOLI</cognome>
<nome>MARINO</nome>
<qualifica></qualifica>
<codfiscale>RTLMRN74S09I138S</codfiscale>
<citta>VALLECROSIA</citta>
<indirizzo>Via Angeli Custodi, n. 111</indirizzo>
<cap>18019</cap>
<provincia>IM</provincia>
</progettisti>
<progettisti>
<codice>72</codice>
<cognome>MARTELLA</cognome>
<nome>WALTER</nome>
<qualifica></qualifica>
<codfiscale>MRTWTR72L18I138T</codfiscale>
<citta>SANREMO</citta>
<indirizzo>via Alessandro Manzoni, 75</indirizzo>
<cap>18038</cap>
<provincia>IM</provincia>
</progettisti>
<progettisti>
<codice>73</codice>
<cognome>CONIO</cognome>
<nome>MARIO</nome>
<qualifica></qualifica>
<codfiscale>CNOMRA71P24I138H</codfiscale>
<citta>TAGGIA</citta>
<indirizzo>VIA L. ARGENTINA N° 23</indirizzo>
<cap>18018</cap>
<provincia>IM</provincia>
</progettisti>
<progettisti>
<codice>74</codice>
<cognome>LANTERI</cognome>
<nome>TIZIANA</nome>
<qualifica></qualifica>
<codfiscale>LNTTZN80A59E290V</codfiscale>
<citta>TAGGIA</citta>
<indirizzo>viale della rimembranza 8</indirizzo>
<cap>18018</cap>
<provincia>IM</provincia>
</progettisti>
<progettisti>
<codice>75</codice>
<cognome>PRATTICO'</cognome>
<nome>ALESSIO</nome>
<qualifica></qualifica>
<codfiscale>PRTLSS85T23A145J</codfiscale>
<citta>TAGGIA</citta>
<indirizzo>via san Francesco, 451</indirizzo>
<cap>1018</cap>
<provincia>IM</provincia>
</progettisti>
<progettisti>
<codice>76</codice>
<cognome>DAMELE</cognome>
<nome>ANTONIO</nome>
<qualifica></qualifica>
<codfiscale>DMLNTN49H16H345P</codfiscale>
<citta>RIVA LIGURE</citta>
<indirizzo>VIA NINO BIXIO 52</indirizzo>
<cap>18015</cap>
<provincia>IM</provincia>
</progettisti>
<progettisti>
<codice>77</codice>
<cognome>BIANCHI</cognome>
<nome>ROMANO</nome>
<qualifica></qualifica>
<codfiscale>BNCRMN61M13A536J</codfiscale>
<citta>SANTO STEFANO AL MARE</citta>
<indirizzo>VIA CARD. MEGLI A  N. 18</indirizzo>
<cap>18010</cap>
<provincia>IM</provincia>
</progettisti>
<progettisti>
<codice>78</codice>
<cognome>AMMENDOLIA</cognome>
<nome>ANDREA</nome>
<qualifica></qualifica>
<codfiscale>MMNNDR76A27I138E</codfiscale>
<citta>SANREMO</citta>
<indirizzo>CORSO GARIBALDI 10</indirizzo>
<cap>18038</cap>
<provincia>IM</provincia>
</progettisti>
<progettisti>
<codice>79</codice>
<cognome>REBAUDO</cognome>
<nome>MATTIA</nome>
<qualifica></qualifica>
<codfiscale>RBDMTT84B28E290U</codfiscale>
<citta>POMPEIANA</citta>
<indirizzo>VIA CAVOUR 51</indirizzo>
<cap>18015</cap>
<provincia>IM</provincia>
</progettisti>
<progettisti>
<codice>80</codice>
<cognome>REBAUDO</cognome>
<nome>MATTIA</nome>
<qualifica></qualifica>
<codfiscale>RBDMTT84B28E290U</codfiscale>
<citta>POMPEIANA</citta>
<indirizzo>VIA CAVOUR 51</indirizzo>
<cap>18015</cap>
<provincia>IM</provincia>
</progettisti>
<progettisti>
<codice>81</codice>
<cognome>BEGHELLO</cognome>
<nome>ILARIA</nome>
<qualifica></qualifica>
<codfiscale>BGHLRI91P59I138B</codfiscale>
<citta>TAGGIA</citta>
<indirizzo>strada castellaro 10</indirizzo>
<cap>18018</cap>
<provincia>IM</provincia>
</progettisti>
<progettisti>
<codice>82</codice>
<cognome>BEGHELLO</cognome>
<nome>ILARIA</nome>
<qualifica></qualifica>
<codfiscale>BGHLRI91P59I138B</codfiscale>
<citta>TAGGIA</citta>
<indirizzo>strada castellaro 10</indirizzo>
<cap>18018</cap>
<provincia>IM</provincia>
</progettisti>
<progettisti>
<codice>83</codice>
<cognome>RICCATO</cognome>
<nome>VIVIANA</nome>
<qualifica></qualifica>
<codfiscale>RCCVVN43A47L781Z</codfiscale>
<citta>TORINO</citta>
<indirizzo>VIA SAN QUINTINO N. 6</indirizzo>
<cap>10121</cap>
<provincia>TO</provincia>
</progettisti>
<progettisti>
<codice>84</codice>
<cognome>ALLAIS</cognome>
<nome>FABRIZIO</nome>
<qualifica></qualifica>
<codfiscale>LLSFRZ77M12D205E</codfiscale>
<citta>BUSCA</citta>
<indirizzo>VIA UMBERTO I N. 44</indirizzo>
<cap>12022</cap>
<provincia>CN</provincia>
</progettisti>
<progettisti>
<codice>85</codice>
<cognome>BOLOGNA</cognome>
<nome>RAFFAELLA</nome>
<qualifica></qualifica>
<codfiscale>BLGRFL73D56G388Y</codfiscale>
<citta>PAVIA</citta>
<indirizzo>VIA SONDRIO, 18</indirizzo>
<cap>18038</cap>
<provincia>PV</provincia>
</progettisti>
<progettisti>
<codice>86</codice>
<cognome>BOLOGNA</cognome>
<nome>RAFFAELLA</nome>
<qualifica></qualifica>
<codfiscale>BLGRFL73D56G388Y</codfiscale>
<citta>PAVIA</citta>
<indirizzo>VIA SONDRIO, 18</indirizzo>
<cap>18038</cap>
<provincia>PV</provincia>
</progettisti>
<progettisti>
<codice>87</codice>
<cognome>RICCI</cognome>
<nome>LISA</nome>
<qualifica></qualifica>
<codfiscale>RCCLSI79E44E290J</codfiscale>
<citta>IMPERIA</citta>
<indirizzo>VIA DELLA FOCE 29/B</indirizzo>
<cap>18100</cap>
<provincia>IM</provincia>
</progettisti>
<progettisti>
<codice>89</codice>
<cognome>DAMELE</cognome>
<nome>ANTONIO</nome>
<qualifica></qualifica>
<codfiscale>DMLNTN49H16H345P</codfiscale>
<citta>RIVA LIGURE</citta>
<indirizzo>VIA NINO BIXIO 52</indirizzo>
<cap>18015</cap>
<provincia>IM</provincia>
</progettisti>
<progettisti>
<codice>90</codice>
<cognome>REBAUDO</cognome>
<nome>MATTIA</nome>
<qualifica></qualifica>
<codfiscale>RBDMTT84B28E290U</codfiscale>
<citta>POMPEIANA</citta>
<indirizzo>VIA CAVOUR 51</indirizzo>
<cap>18015</cap>
<provincia>IM</provincia>
</progettisti>
<progettisti>
<codice>91</codice>
<cognome>SECONDO</cognome>
<nome>DIMITRI</nome>
<qualifica></qualifica>
<codfiscale>SCNDTR71M29I138B</codfiscale>
<citta>TAGGIA</citta>
<indirizzo>via Boselli 19</indirizzo>
<cap>18018</cap>
<provincia>IM</provincia>
</progettisti>
<progettisti>
<codice>92</codice>
<cognome>STICOZZI</cognome>
<nome>TIZIANA CELESTINA PIA</nome>
<qualifica></qualifica>
<codfiscale>STCTNC78A55H926K</codfiscale>
<citta>GIVOLETTO</citta>
<indirizzo>Via La Cassa 63</indirizzo>
<cap>10040</cap>
<provincia>TO</provincia>
</progettisti>
<progettisti>
<codice>93</codice>
<cognome>GIORGINI</cognome>
<nome>GIAN CARLO</nome>
<qualifica></qualifica>
<codfiscale>GRGGCR60R30I829W</codfiscale>
<citta>SANTO STEFANO AL MARE</citta>
<indirizzo>lungomare C. Colombo, 76b</indirizzo>
<cap>18010</cap>
<provincia>IM</provincia>
</progettisti>
<progettisti>
<codice>94</codice>
<cognome>PRATTICO'</cognome>
<nome>ALESSIO</nome>
<qualifica></qualifica>
<codfiscale>PRTLSS85T23A145J</codfiscale>
<citta>TAGGIA</citta>
<indirizzo>via san Francesco, 451</indirizzo>
<cap>1018</cap>
<provincia>IM</provincia>
</progettisti>
<progettisti>
<codice>95</codice>
<cognome>GAIDO</cognome>
<nome>RENZO</nome>
<qualifica></qualifica>
<codfiscale>GDARNZ70H29G674T</codfiscale>
<citta>VILLAR PEROSA</citta>
<indirizzo>VIA NAZIONALE 39</indirizzo>
<cap>10069</cap>
<provincia>TO</provincia>
</progettisti>
<progettisti>
<codice>96</codice>
<cognome>CENEDESE</cognome>
<nome>DANIEL</nome>
<qualifica></qualifica>
<codfiscale>CNDDNL72P01L219P</codfiscale>
<citta>GRUGLIASCO</citta>
<indirizzo>VIALE ANTONIO GRAMSCI N°108/A</indirizzo>
<cap>10095</cap>
<provincia>TO</provincia>
</progettisti>
<progettisti>
<codice>97</codice>
<cognome>REBAUDO</cognome>
<nome>MATTIA</nome>
<qualifica></qualifica>
<codfiscale>RBDMTT84B28E290U</codfiscale>
<citta>POMPEIANA</citta>
<indirizzo>VIA CAVOUR 51</indirizzo>
<cap>18015</cap>
<provincia>IM</provincia>
</progettisti>
<progettisti>
<codice>98</codice>
<cognome>CARLI</cognome>
<nome>ORNELLA</nome>
<qualifica></qualifica>
<codfiscale>CRLRLL68H67I138V</codfiscale>
<citta>TAGGIA</citta>
<indirizzo>VIA GENOVA 4</indirizzo>
<cap>18018</cap>
<provincia>IM</provincia>
</progettisti>
<progettisti>
<codice>99</codice>
<cognome>EREDDIA</cognome>
<nome>FABRIZIO</nome>
<qualifica></qualifica>
<codfiscale>RDDFRZ84S03E290N</codfiscale>
<citta>IMPERIA</citta>
<indirizzo>VIA SILVIO BONFANTE, 23</indirizzo>
<cap>18100</cap>
<provincia>IM</provincia>
</progettisti>
<progettisti>
<codice>100</codice>
<cognome>MEROGNO</cognome>
<nome>DANILO</nome>
<qualifica></qualifica>
<codfiscale>MRGDNL73E25I138C</codfiscale>
<citta>TAGGIA</citta>
<indirizzo>VIA C. COLOMBO 52</indirizzo>
<cap>18018</cap>
<provincia>IM</provincia>
</progettisti>
<progettisti>
<codice>101</codice>
<cognome>REBAUDO</cognome>
<nome>MATTIA</nome>
<qualifica></qualifica>
<codfiscale>RBDMTT84B28E290U</codfiscale>
<citta>POMPEIANA</citta>
<indirizzo>VIA CAVOUR 51</indirizzo>
<cap>18015</cap>
<provincia>IM</provincia>
</progettisti>
<progettisti>
<codice>102</codice>
<cognome>REBAUDO</cognome>
<nome>MATTIA</nome>
<qualifica></qualifica>
<codfiscale>RBDMTT84B28E290U</codfiscale>
<citta>POMPEIANA</citta>
<indirizzo>VIA CAVOUR 51</indirizzo>
<cap>18015</cap>
<provincia>IM</provincia>
</progettisti>
<progettisti>
<codice>103</codice>
<cognome>MONTANARO</cognome>
<nome>ADRIANO</nome>
<qualifica></qualifica>
<codfiscale>MNTDRN54A28L219Q</codfiscale>
<citta>SANGANO</citta>
<indirizzo>VIA PINEROLO-SUSA 63</indirizzo>
<cap>10090</cap>
<provincia>TO</provincia>
</progettisti>
<progettisti>
<codice>104</codice>
<cognome>ALLARME</cognome>
<nome>FABRIZIO</nome>
<qualifica></qualifica>
<codfiscale>LLRFRZ70H28A479X</codfiscale>
<citta>COSTIGLIOLE D'ASTI</citta>
<indirizzo>VIA ALBA 74</indirizzo>
<cap>14055</cap>
<provincia>AT</provincia>
</progettisti>
<progettisti>
<codice>106</codice>
<cognome>AMMIRATI</cognome>
<nome>ALBERTO</nome>
<qualifica></qualifica>
<codfiscale>MMRLRT58E31I138J</codfiscale>
<citta>CIPRESSA</citta>
<indirizzo>VIA FOSSATI, 25</indirizzo>
<cap>18017</cap>
<provincia>IM</provincia>
</progettisti>
<progettisti>
<codice>107</codice>
<cognome>REBAUDO</cognome>
<nome>MATTIA</nome>
<qualifica></qualifica>
<codfiscale>RBDMTT84B28E290U</codfiscale>
<citta>POMPEIANA</citta>
<indirizzo>VIA CAVOUR 51</indirizzo>
<cap>18015</cap>
<provincia>IM</provincia>
</progettisti>
<progettisti>
<codice>108</codice>
<cognome>REBAUDO</cognome>
<nome>MATTIA</nome>
<qualifica></qualifica>
<codfiscale>RBDMTT84B28E290U</codfiscale>
<citta>POMPEIANA</citta>
<indirizzo>VIA CAVOUR 51</indirizzo>
<cap>18015</cap>
<provincia>IM</provincia>
</progettisti>
<progettisti>
<codice>109</codice>
<cognome>REBAUDO</cognome>
<nome>MATTIA</nome>
<qualifica></qualifica>
<codfiscale>RBDMTT84B28E290U</codfiscale>
<citta>POMPEIANA</citta>
<indirizzo>VIA CAVOUR 51</indirizzo>
<cap>18015</cap>
<provincia>IM</provincia>
</progettisti>
<progettisti>
<codice>110</codice>
<cognome>REBAUDO</cognome>
<nome>MATTIA</nome>
<qualifica></qualifica>
<codfiscale>RBDMTT84B28E290U</codfiscale>
<citta>POMPEIANA</citta>
<indirizzo>VIA CAVOUR 51</indirizzo>
<cap>18015</cap>
<provincia>IM</provincia>
</progettisti>
<progettisti>
<codice>111</codice>
<cognome>REBAUDO</cognome>
<nome>IVANO</nome>
<qualifica></qualifica>
<codfiscale>RBDVNI58P27E290X</codfiscale>
<citta>SANTO STEFANO AL MARE</citta>
<indirizzo>VIA ROMA 28</indirizzo>
<cap>18010</cap>
<provincia>IM</provincia>
</progettisti>
<progettisti>
<codice>112</codice>
<cognome>REBAUDO</cognome>
<nome>MATTIA</nome>
<qualifica></qualifica>
<codfiscale>RBDMTT84B28E290U</codfiscale>
<citta>POMPEIANA</citta>
<indirizzo>VIA CAVOUR 51</indirizzo>
<cap>18015</cap>
<provincia>IM</provincia>
</progettisti>
<progettisti>
<codice>113</codice>
<cognome>COGGIOLA</cognome>
<nome>AMERIGO</nome>
<qualifica></qualifica>
<codfiscale>CGGMRG54E04I138N</codfiscale>
<citta>CASTELLARO</citta>
<indirizzo>CORSO DANTE ALIGHIERI, 8</indirizzo>
<cap>18011</cap>
<provincia>IM</provincia>
</progettisti>
<progettisti>
<codice>114</codice>
<cognome>RICCATO</cognome>
<nome>VIVIANA</nome>
<qualifica></qualifica>
<codfiscale>RCCVVN43A47L781Z</codfiscale>
<citta>TORINO</citta>
<indirizzo>VIA SAN QUINTINO N. 6</indirizzo>
<cap>10121</cap>
<provincia>TO</provincia>
</progettisti>
<progettisti>
<codice>115</codice>
<cognome>CONIO</cognome>
<nome>MARIO</nome>
<qualifica></qualifica>
<codfiscale>CNOMRA71P24I138H</codfiscale>
<citta>TAGGIA</citta>
<indirizzo>VIA L.ARGENTINA N.23</indirizzo>
<cap>18018</cap>
<provincia>IM</provincia>
</progettisti>
<progettisti>
<codice>116</codice>
<cognome>OLIVIERI</cognome>
<nome>MATTIA</nome>
<qualifica></qualifica>
<codfiscale>LVRMTT86P26E290M</codfiscale>
<citta>IMPERIA</citta>
<indirizzo>via de tommaso 30</indirizzo>
<cap>18100</cap>
<provincia>IM</provincia>
</progettisti>
<progettisti>
<codice>117</codice>
<cognome>CALDARELLI</cognome>
<nome>MARCO</nome>
<qualifica></qualifica>
<codfiscale>CLDMRC57D08D548A</codfiscale>
<citta>SANREMO</citta>
<indirizzo>via G. Pallavicino, 6</indirizzo>
<cap>18038</cap>
<provincia>IM</provincia>
</progettisti>
<progettisti>
<codice>118</codice>
<cognome>AIMONE SECAT</cognome>
<nome>VICTORIA</nome>
<qualifica></qualifica>
<codfiscale>MNSVTR88T47L219N</codfiscale>
<citta>TORINO</citta>
<indirizzo>Corso C. Correnti 37</indirizzo>
<cap>10136</cap>
<provincia>TO</provincia>
</progettisti>
<progettisti>
<codice>119</codice>
<cognome>DAMELE</cognome>
<nome>ANTONIO</nome>
<qualifica></qualifica>
<codfiscale>DMLNTN49H16H345P</codfiscale>
<citta>RIVA LIGURE</citta>
<indirizzo>VIA NINO BIXIO 52</indirizzo>
<cap>18015</cap>
<provincia>IM</provincia>
</progettisti>
<progettisti>
<codice>120</codice>
<cognome>ROGGERI</cognome>
<nome>MARCO</nome>
<qualifica></qualifica>
<codfiscale>RGGMRC69S07I138E</codfiscale>
<citta>SANTO STEFANO AL MARE</citta>
<indirizzo>via Cardinal Meglia 28</indirizzo>
<cap>18010</cap>
<provincia>IM</provincia>
</progettisti>
<progettisti>
<codice>121</codice>
<cognome>BEGHELLO</cognome>
<nome>ILARIA</nome>
<qualifica></qualifica>
<codfiscale>BGHLRI91P59I138B</codfiscale>
<citta>TAGGIA</citta>
<indirizzo>strada castellaro 10</indirizzo>
<cap>18018</cap>
<provincia>IM</provincia>
</progettisti>
<progettisti>
<codice>122</codice>
<cognome>AMMIRATI</cognome>
<nome>ALBERTO</nome>
<qualifica></qualifica>
<codfiscale>MMRLRT58E31I138J</codfiscale>
<citta>CIPRESSA</citta>
<indirizzo>VIA AVV. M. FOSSATI 25</indirizzo>
<cap>18017</cap>
<provincia>IM</provincia>
</progettisti>
<progettisti>
<codice>123</codice>
<cognome>ROGGERI</cognome>
<nome>MARCO</nome>
<qualifica></qualifica>
<codfiscale>RGGMRC69S07I138E</codfiscale>
<citta>SANTO STEFANO AL MARE</citta>
<indirizzo>via Cardinal Meglia 28</indirizzo>
<cap>18010</cap>
<provincia>IM</provincia>
</progettisti>
<progettisti>
<codice>124</codice>
<cognome>ALAURIA</cognome>
<nome>SIMONA</nome>
<qualifica></qualifica>
<codfiscale>LRASMN75C50L219M</codfiscale>
<citta>OSPEDALETTI</citta>
<indirizzo>CORSO REGINA MARGHERITA 13</indirizzo>
<cap>18014</cap>
<provincia>IM</provincia>
</progettisti>
<progettisti>
<codice>125</codice>
<cognome>MARTINO</cognome>
<nome>DONATELLA</nome>
<qualifica></qualifica>
<codfiscale>MRTDTL98P52F351G</codfiscale>
<citta>SAN MICHELE MONDOVÌ</citta>
<indirizzo>VIA MOIE NR.20</indirizzo>
<cap>12080</cap>
<provincia>CN</provincia>
</progettisti>
<progettisti>
<codice>126</codice>
<cognome>REBAUDO</cognome>
<nome>IVANO</nome>
<qualifica></qualifica>
<codfiscale>RBDVNI58P27E290X</codfiscale>
<citta>SANTO STEFANO AL MARE</citta>
<indirizzo>VIA ROMA 28</indirizzo>
<cap>18010</cap>
<provincia>IM</provincia>
</progettisti>
<progettisti>
<codice>127</codice>
<cognome>MARSIGLIA</cognome>
<nome>GIOVANNI</nome>
<qualifica></qualifica>
<codfiscale>MRSGNN60T09E290Z</codfiscale>
<citta>SANREMO</citta>
<indirizzo>via Ruffini 19</indirizzo>
<cap>18038</cap>
<provincia>IM</provincia>
</progettisti>
<progettisti>
<codice>128</codice>
<cognome>NATTA</cognome>
<nome>MIRKO</nome>
<qualifica></qualifica>
<codfiscale>NTTMRK85T14E290U</codfiscale>
<citta>IMPERIA</citta>
<indirizzo>via san leonardo,54</indirizzo>
<cap>18100</cap>
<provincia>IM</provincia>
</progettisti>
<progettisti>
<codice>129</codice>
<cognome>SABLONE</cognome>
<nome>LORENA</nome>
<qualifica></qualifica>
<codfiscale>SBLLRN69B42E290X</codfiscale>
<citta>RIVA LIGURE</citta>
<indirizzo>VIA GARIBALDI 32 BIS</indirizzo>
<cap>18015</cap>
<provincia>IM</provincia>
</progettisti>
<progettisti>
<codice>130</codice>
<cognome>CASTAGNINO</cognome>
<nome>GUIDO</nome>
<qualifica></qualifica>
<codfiscale>CSTGDU84T07I138Y</codfiscale>
<citta>ARMA DI TAGGIA</citta>
<indirizzo>TRAVERSA DI VIA CASTELLETTI n° 33/1</indirizzo>
<cap>18018</cap>
<provincia>IM</provincia>
</progettisti>
<progettisti>
<codice>131</codice>
<cognome>CASTAGNINO</cognome>
<nome>GUIDO</nome>
<qualifica></qualifica>
<codfiscale>CSTGDU84T07I138Y</codfiscale>
<citta>ARMA DI TAGGIA</citta>
<indirizzo>TRAVERSA DI VIA CASTELLETTI 33/1</indirizzo>
<cap>18018</cap>
<provincia>IM</provincia>
</progettisti>
<progettisti>
<codice>132</codice>
<cognome>PAPADIA</cognome>
<nome>MATTEO</nome>
<qualifica></qualifica>
<codfiscale>PPDMTT75T16H264T</codfiscale>
<citta>MILANO</citta>
<indirizzo>VIA N. BIXIO 27</indirizzo>
<cap>20129</cap>
<provincia>MI</provincia>
</progettisti>
<progettisti>
<codice>133</codice>
<cognome>CASTAGNINO</cognome>
<nome>GUIDO</nome>
<qualifica></qualifica>
<codfiscale>CSTGDU84T07I138Y</codfiscale>
<citta>TAGGIA</citta>
<indirizzo>TRAVERSA DI VIA CASTELLETTI 33/1</indirizzo>
<cap>18018</cap>
<provincia>IM</provincia>
</progettisti>
<progettisti>
<codice>134</codice>
<cognome>DAMELE</cognome>
<nome>ANTONIO</nome>
<qualifica></qualifica>
<codfiscale>DMLNTN49H16H345P</codfiscale>
<citta>RIVA LIGURE</citta>
<indirizzo>VIA NINO BIXIO 52</indirizzo>
<cap>18015</cap>
<provincia>IM</provincia>
</progettisti>
<progettisti>
<codice>135</codice>
<cognome>BEGHELLO</cognome>
<nome>ILARIA</nome>
<qualifica></qualifica>
<codfiscale>BGHLRI91P59I138B</codfiscale>
<citta>TAGGIA</citta>
<indirizzo>strada castellaro 10</indirizzo>
<cap>18018</cap>
<provincia>IM</provincia>
</progettisti>
<progettisti>
<codice>136</codice>
<cognome>VENTURI</cognome>
<nome>ALEX</nome>
<qualifica></qualifica>
<codfiscale>VNTLXA90C21G999C</codfiscale>
<citta>TAGGIA</citta>
<indirizzo>VIA II TRAVERSA CORNICE 31</indirizzo>
<cap>18018</cap>
<provincia>IM</provincia>
</progettisti>
<progettisti>
<codice>137</codice>
<cognome>BEGHELLO</cognome>
<nome>ILARIA</nome>
<qualifica></qualifica>
<codfiscale>BGHLRI91P59I138B</codfiscale>
<citta>TAGGIA</citta>
<indirizzo>strada castellaro 10</indirizzo>
<cap>18018</cap>
<provincia>IM</provincia>
</progettisti>
<progettisti>
<codice>138</codice>
<cognome>DAMELE</cognome>
<nome>ANTONIO</nome>
<qualifica></qualifica>
<codfiscale>DMLNTN49H16H345P</codfiscale>
<citta>RIVA LIGURE</citta>
<indirizzo>VIA NINO BIXIO 52</indirizzo>
<cap>18015</cap>
<provincia>IM</provincia>
</progettisti>
<progettisti>
<codice>139</codice>
<cognome>DAMELE</cognome>
<nome>ANTONIO</nome>
<qualifica></qualifica>
<codfiscale>DMLNTN49H16H345P</codfiscale>
<citta>RIVA LIGURE</citta>
<indirizzo>VIA NINO BIXIO 52</indirizzo>
<cap>18015</cap>
<provincia>IM</provincia>
</progettisti>
<progettisti>
<codice>140</codice>
<cognome>SAPPA</cognome>
<nome>VALENTINO</nome>
<qualifica></qualifica>
<codfiscale>SPPVNT87H04E290F</codfiscale>
<citta>SANREMO</citta>
<indirizzo>VIA DANTE ALIGHIERI 56</indirizzo>
<cap>18038</cap>
<provincia>IM</provincia>
</progettisti>
<progettisti>
<codice>141</codice>
<cognome>DAPRELA'</cognome>
<nome>MICHEL</nome>
<qualifica></qualifica>
<codfiscale>DPRMHL74R07E290F</codfiscale>
<citta>IMPERIA</citta>
<indirizzo>via xxv aprile 91b</indirizzo>
<cap>18100</cap>
<provincia>IM</provincia>
</progettisti>
<progettisti>
<codice>142</codice>
<cognome>MICHELETTI</cognome>
<nome>MARCO</nome>
<qualifica></qualifica>
<codfiscale>MCHMRC81C05L219F</codfiscale>
<citta>VALLO TORINESE</citta>
<indirizzo>VIA MONASTEROLO N° 2</indirizzo>
<cap>10070</cap>
<provincia>TO</provincia>
</progettisti>
<progettisti>
<codice>143</codice>
<cognome>DAMELE</cognome>
<nome>ANTONIO</nome>
<qualifica></qualifica>
<codfiscale>DMLNTN49H16H345P</codfiscale>
<citta>RIVA LIGURE</citta>
<indirizzo>VIA NINO BIXIO 52</indirizzo>
<cap>18015</cap>
<provincia>IM</provincia>
</progettisti>
<progettisti>
<codice>144</codice>
<cognome>MICHELETTI</cognome>
<nome>MARCO</nome>
<qualifica></qualifica>
<codfiscale>MCHMRC81C05L219F</codfiscale>
<citta>VALLO TORINESE</citta>
<indirizzo>VIA MONASTEROLO N° 2</indirizzo>
<cap>10070</cap>
<provincia>TO</provincia>
</progettisti>
<progettisti>
<codice>145</codice>
<cognome>TAGLIATINI</cognome>
<nome>ALBERTO</nome>
<qualifica></qualifica>
<codfiscale>TGLLRT77M02I138J</codfiscale>
<citta>ARMA DI TAGGIA</citta>
<indirizzo>Via Cornice n.78/a - Taggia</indirizzo>
<cap>18013</cap>
<provincia>IM</provincia>
</progettisti>
<progettisti>
<codice>146</codice>
<cognome>REBAUDO</cognome>
<nome>IVANO</nome>
<qualifica></qualifica>
<codfiscale>RBDVNI58P27E290X</codfiscale>
<citta>SANTO STEFANO AL MARE</citta>
<indirizzo>VIA ROMA 28</indirizzo>
<cap>18010</cap>
<provincia>IM</provincia>
</progettisti>
<progettisti>
<codice>147</codice>
<cognome>SAPPA</cognome>
<nome>VALENTINO</nome>
<qualifica></qualifica>
<codfiscale>SPPVNT87H04E290F</codfiscale>
<citta>SANREMO</citta>
<indirizzo>VIA DANTE ALIGHIERI 56</indirizzo>
<cap>18038</cap>
<provincia>IM</provincia>
</progettisti>
<progettisti>
<codice>148</codice>
<cognome>REBAUDO</cognome>
<nome>MATTIA</nome>
<qualifica></qualifica>
<codfiscale>RBDMTT84B28E290U</codfiscale>
<citta>POMPEIANA</citta>
<indirizzo>VIA CAVOUR 51</indirizzo>
<cap>18015</cap>
<provincia>IM</provincia>
</progettisti>
<progettisti>
<codice>149</codice>
<cognome>CAPPONI</cognome>
<nome>DAMIANO</nome>
<qualifica></qualifica>
<codfiscale>CPPDMN91P16I138Y</codfiscale>
<citta>CASTELLARO</citta>
<indirizzo>Via Lampedusa n.51</indirizzo>
<cap>18011</cap>
<provincia>IM</provincia>
</progettisti>
<progettisti>
<codice>150</codice>
<cognome>AMMIRATI</cognome>
<nome>ALBERTO</nome>
<qualifica></qualifica>
<codfiscale>MMRLRT58E31I138J</codfiscale>
<citta>CIPRESSA</citta>
<indirizzo>VIA AVV. M. FOSSATI, 25</indirizzo>
<cap>18017</cap>
<provincia>IM</provincia>
</progettisti>
<progettisti>
<codice>151</codice>
<cognome>BERTANI</cognome>
<nome>FABIO</nome>
<qualifica></qualifica>
<codfiscale>BRTFBA71C30E290E</codfiscale>
<citta>TAGGIA</citta>
<indirizzo>VIA DEL FORNO 2</indirizzo>
<cap>18018</cap>
<provincia>IM</provincia>
</progettisti>
<progettisti>
<codice>152</codice>
<cognome>ARENA</cognome>
<nome>SANDRO</nome>
<qualifica></qualifica>
<codfiscale>RNASDR68R08I138O</codfiscale>
<citta>SANREMO</citta>
<indirizzo>C.SO INGLESI, 75</indirizzo>
<cap>18038</cap>
<provincia>IM</provincia>
</progettisti>
<progettisti>
<codice>153</codice>
<cognome>MERANO</cognome>
<nome>ANNACLETA</nome>
<qualifica></qualifica>
<codfiscale>MRNNCL53C67B020D</codfiscale>
<citta>TAGGIA</citta>
<indirizzo>TRAVERSA DI VIA CASTELLETTI, 33/1</indirizzo>
<cap>18018</cap>
<provincia>IM</provincia>
</progettisti>
<progettisti>
<codice>154</codice>
<cognome>LANZONE</cognome>
<nome>DAVIDE</nome>
<qualifica></qualifica>
<codfiscale>LNZDVD78R08E290X</codfiscale>
<citta>IMPERIA</citta>
<indirizzo>Via A. Canova 24</indirizzo>
<cap>18100</cap>
<provincia>IM</provincia>
</progettisti>
<progettisti>
<codice>155</codice>
<cognome>PEREGO</cognome>
<nome>MASSIMO</nome>
<qualifica></qualifica>
<codfiscale>PRGMSM58C05I138K</codfiscale>
<citta>SANREMO</citta>
<indirizzo>piazza San Siro 48</indirizzo>
<cap>18038</cap>
<provincia>IM</provincia>
</progettisti>
<progettisti>
<codice>156</codice>
<cognome>ROGGERI</cognome>
<nome>MARCO</nome>
<qualifica></qualifica>
<codfiscale>RGGMRC69S07I138E</codfiscale>
<citta>SANTO STEFANO AL MARE</citta>
<indirizzo>via Cardinal Meglia 28</indirizzo>
<cap>18010</cap>
<provincia>IM</provincia>
</progettisti>
<progettisti>
<codice>157</codice>
<cognome>ROGGERI</cognome>
<nome>MARCO</nome>
<qualifica></qualifica>
<codfiscale>RGGMRC69S07I138E</codfiscale>
<citta>SANTO STEFANO AL MARE</citta>
<indirizzo>via Cardinal Meglia 28</indirizzo>
<cap>18010</cap>
<provincia>IM</provincia>
</progettisti>
<progettisti>
<codice>158</codice>
<cognome>LANZONE</cognome>
<nome>DAVIDE</nome>
<qualifica></qualifica>
<codfiscale>LNZDVD78R08E290X</codfiscale>
<citta>IMPERIA</citta>
<indirizzo>Via Santa Lucia 95</indirizzo>
<cap>18100</cap>
<provincia>IM</provincia>
</progettisti>
<progettisti>
<codice>159</codice>
<cognome>SABLONE</cognome>
<nome>LORENA</nome>
<qualifica></qualifica>
<codfiscale>SBLLRN69B42E290X</codfiscale>
<citta>RIVA LIGURE</citta>
<indirizzo>VIA GARIBALDI 32 BIS</indirizzo>
<cap>18015</cap>
<provincia>IM</provincia>
</progettisti>
<progettisti>
<codice>160</codice>
<cognome>FERRUA</cognome>
<nome>CLAUDIO</nome>
<qualifica></qualifica>
<codfiscale>FRRCLD76T06A984H</codfiscale>
<citta>CAMPOROSSO</citta>
<indirizzo>VIA ALESSANDRO MANZONI 51</indirizzo>
<cap>18033</cap>
<provincia>IM</provincia>
</progettisti>
<progettisti>
<codice>161</codice>
<cognome>GIAUNI</cognome>
<nome>LUCA</nome>
<qualifica></qualifica>
<codfiscale>GNILCU75D03I138T</codfiscale>
<citta>SANREMO</citta>
<indirizzo>VIA G. GALILEI n. 371</indirizzo>
<cap>18038</cap>
<provincia>IM</provincia>
</progettisti>
<progettisti>
<codice>162</codice>
<cognome>RODA'</cognome>
<nome>MONICA</nome>
<qualifica></qualifica>
<codfiscale>RDOMNC74H47I138P</codfiscale>
<citta>SANREMO</citta>
<indirizzo>str. Senatore E. Marsaglia n.364</indirizzo>
<cap>18038</cap>
<provincia>IM</provincia>
</progettisti>
<progettisti>
<codice>163</codice>
<cognome>DAMELE</cognome>
<nome>ANTONIO</nome>
<qualifica></qualifica>
<codfiscale>DMLNTN49H16H345P</codfiscale>
<citta>RIVA LIGURE</citta>
<indirizzo>VIA NINO BIXIO 52</indirizzo>
<cap>18015</cap>
<provincia>IM</provincia>
</progettisti>
<progettisti>
<codice>164</codice>
<cognome>COLANGELO</cognome>
<nome>GIANFRANCESCO</nome>
<qualifica></qualifica>
<codfiscale>CLNGFR75P25F205F</codfiscale>
<citta>SANREMO</citta>
<indirizzo>VIA W GOETHE 35</indirizzo>
<cap>18038</cap>
<provincia>IM</provincia>
</progettisti>
<progettisti>
<codice>165</codice>
<cognome>SICCARDI</cognome>
<nome>ROBERTO</nome>
<qualifica></qualifica>
<codfiscale>SCCRRT70S23I138B</codfiscale>
<citta>TAGGIA</citta>
<indirizzo>VIA A. DORIA n. 32</indirizzo>
<cap>18018</cap>
<provincia>IM</provincia>
</progettisti>
<progettisti>
<codice>166</codice>
<cognome>FERRUA</cognome>
<nome>CLAUDIO FERRUA</nome>
<qualifica></qualifica>
<codfiscale>FRRCLD76T06A984H</codfiscale>
<citta>CAMPOROSSO</citta>
<indirizzo>VIA ALESSANDRO MANZONI 51</indirizzo>
<cap>18033</cap>
<provincia>IM</provincia>
</progettisti>
<progettisti>
<codice>167</codice>
<cognome>CONIO</cognome>
<nome>MARIO</nome>
<qualifica></qualifica>
<codfiscale>CNOMRA71P24I138H</codfiscale>
<citta>TAGGIA</citta>
<indirizzo>VIA L. ARGENTINA N° 23</indirizzo>
<cap>18018</cap>
<provincia>IM</provincia>
</progettisti>
<progettisti>
<codice>168</codice>
<cognome>FERRUA</cognome>
<nome>CLAUDIO FERRUA</nome>
<qualifica></qualifica>
<codfiscale>FRRCLD76T06A984H</codfiscale>
<citta>CAMPOROSSO</citta>
<indirizzo>VIA ALESSANDRO MANZONI 51</indirizzo>
<cap>18033</cap>
<provincia>IM</provincia>
</progettisti>
<progettisti>
<codice>169</codice>
<cognome>MARVALDI</cognome>
<nome>LUCA MARVALDI</nome>
<qualifica></qualifica>
<codfiscale>MRVLCU78E02E290J</codfiscale>
<citta>SANREMO</citta>
<indirizzo>piazza muccioli 7</indirizzo>
<cap>18038</cap>
<provincia>IM</provincia>
</progettisti>
<progettisti>
<codice>170</codice>
<cognome>EREDDIA</cognome>
<nome>FABRIZIO</nome>
<qualifica></qualifica>
<codfiscale>RDDFRZ84S03E290N</codfiscale>
<citta>IMPERIA</citta>
<indirizzo>via bonfante 23</indirizzo>
<cap>18100</cap>
<provincia>IM</provincia>
</progettisti>
<progettisti>
<codice>171</codice>
<cognome>EREDDIA</cognome>
<nome>FABRIZIO</nome>
<qualifica></qualifica>
<codfiscale>RDDFRZ84S03E290N</codfiscale>
<citta>IMPERIA</citta>
<indirizzo>VIA SILVIO BONFANTE, 23</indirizzo>
<cap>18100</cap>
<provincia>IM</provincia>
</progettisti>
<progettisti>
<codice>172</codice>
<cognome>CENEDESE</cognome>
<nome>DANIEL</nome>
<qualifica></qualifica>
<codfiscale>CNDDNL72P01L219P</codfiscale>
<citta>GRUGLIASCO</citta>
<indirizzo>VIALE ANTONIO GRAMSCI N°108/A</indirizzo>
<cap>10095</cap>
<provincia>TO</provincia>
</progettisti>
<progettisti>
<codice>173</codice>
<cognome>SABLONE</cognome>
<nome>LORENA</nome>
<qualifica></qualifica>
<codfiscale>SBLLRN69B42E290X</codfiscale>
<citta>RIVA LIGURE</citta>
<indirizzo>VIA GARIBALDI 32 BIS</indirizzo>
<cap>18015</cap>
<provincia>IM</provincia>
</progettisti>
<progettisti>
<codice>174</codice>
<cognome>VENTURI</cognome>
<nome>ALEX</nome>
<qualifica></qualifica>
<codfiscale>VNTLXA90C21G999C</codfiscale>
<citta>TAGGIA</citta>
<indirizzo>via II TRAVERSA DELLA CORNICE 31</indirizzo>
<cap>18018</cap>
<provincia>IM</provincia>
</progettisti>
<progettisti>
<codice>175</codice>
<cognome>ROGGERI</cognome>
<nome>GIOVANNI</nome>
<qualifica></qualifica>
<codfiscale>RGGGNN60E14I138C</codfiscale>
<citta>S. STEFANO AL MARE</citta>
<indirizzo>VIA CARDINALE MEGLIA, 24</indirizzo>
<cap>18010</cap>
<provincia>IM</provincia>
</progettisti>
<progettisti>
<codice>176</codice>
<cognome>VENTURI</cognome>
<nome>ALEX</nome>
<qualifica></qualifica>
<codfiscale>VNTLXA90C21G999C</codfiscale>
<citta>TAGGIA</citta>
<indirizzo>VIA II TRAVERSA DELLA CORNICE 31</indirizzo>
<cap>18018</cap>
<provincia>IM</provincia>
</progettisti>
<progettisti>
<codice>177</codice>
<cognome>MAGNA</cognome>
<nome>LORENZO</nome>
<qualifica></qualifica>
<codfiscale>MGNLNZ85H19I138L</codfiscale>
<citta>SANTO STEFANO AL MARE</citta>
<indirizzo>VIA MOSCATELLI 7</indirizzo>
<cap>18010</cap>
<provincia>IM</provincia>
</progettisti>
<progettisti>
<codice>178</codice>
<cognome>DAMELE</cognome>
<nome>ANTONIO</nome>
<qualifica></qualifica>
<codfiscale>DMLNTN49H16H345P</codfiscale>
<citta>RIVA LIGURE</citta>
<indirizzo>VIA NINO BIXIO 52</indirizzo>
<cap>18015</cap>
<provincia>IM</provincia>
</progettisti>
<progettisti>
<codice>179</codice>
<cognome>CHIESA</cognome>
<nome>MARIASERENA</nome>
<qualifica></qualifica>
<codfiscale>CHSMSR69E68F205Q</codfiscale>
<citta>MILANO</citta>
<indirizzo>VIA DEI MISSAGLIA</indirizzo>
<cap>20</cap>
<provincia>MI</provincia>
</progettisti>
<progettisti>
<codice>180</codice>
<cognome>DAMELE</cognome>
<nome>ANTONIO</nome>
<qualifica></qualifica>
<codfiscale>DMLNTN49H16H345P</codfiscale>
<citta>RIVA LIGURE</citta>
<indirizzo>VIA NINO BIXIO 52</indirizzo>
<cap>18015</cap>
<provincia>IM</provincia>
</progettisti>
<progettisti>
<codice>182</codice>
<cognome>GIORGINI</cognome>
<nome>GIAN CARLO</nome>
<qualifica></qualifica>
<codfiscale>GRGGCR60R30I829W</codfiscale>
<citta>SANTO STEFANO AL MARE</citta>
<indirizzo>Lungomare C. Colombo, 76b</indirizzo>
<cap>18010</cap>
<provincia>IM</provincia>
</progettisti>
<progettisti>
<codice>183</codice>
<cognome>MARSIGLIA</cognome>
<nome>GIOVANNI</nome>
<qualifica></qualifica>
<codfiscale>MRSGNN60T09E290Z</codfiscale>
<citta>SANREMO</citta>
<indirizzo>VIA RUFFINI 19</indirizzo>
<cap>18038</cap>
<provincia>IM</provincia>
</progettisti>
<progettisti>
<codice>184</codice>
<cognome>MARSIGLIA</cognome>
<nome>GIOVANNI</nome>
<qualifica></qualifica>
<codfiscale>MRSGNN60T09E290Z</codfiscale>
<citta>SANREMO</citta>
<indirizzo>VIA RUFFINI 19</indirizzo>
<cap>18038</cap>
<provincia>IM</provincia>
</progettisti>
<progettisti>
<codice>185</codice>
<cognome>DAMELE</cognome>
<nome>ANTONIO</nome>
<qualifica></qualifica>
<codfiscale>DMLNTN49H16H345P</codfiscale>
<citta>RIVA LIGURE</citta>
<indirizzo>VIA NINO BIXIO 52</indirizzo>
<cap>18015</cap>
<provincia>IM</provincia>
</progettisti>
<progettisti>
<codice>186</codice>
<cognome>MODENA</cognome>
<nome>GIANFRANCO</nome>
<qualifica></qualifica>
<codfiscale>MDNGFR59R28I138C</codfiscale>
<citta>SANREMO</citta>
<indirizzo>via Privata Peiranze 17/9</indirizzo>
<cap>18038</cap>
<provincia>IM</provincia>
</progettisti>
<progettisti>
<codice>187</codice>
<cognome>CORDEGLIO</cognome>
<nome>LUCA</nome>
<qualifica></qualifica>
<codfiscale>CRDLSC79R22E290K</codfiscale>
<citta>SAN LORENZO AL MARE</citta>
<indirizzo>VIA AURELIA N. 110</indirizzo>
<cap>18010</cap>
<provincia>IM</provincia>
</progettisti>
<progettisti>
<codice>188</codice>
<cognome>DEMARIA</cognome>
<nome>ALBERTO</nome>
<qualifica></qualifica>
<codfiscale>DMRLRT79D02D205U</codfiscale>
<citta>REVELLO</citta>
<indirizzo>VIA GIOVANNI GIOLITTI 4</indirizzo>
<cap>12036</cap>
<provincia>CN</provincia>
</progettisti>
<progettisti>
<codice>189</codice>
<cognome>PRATTICO'</cognome>
<nome>ALESSIO</nome>
<qualifica></qualifica>
<codfiscale>PRTLSS85T23A145J</codfiscale>
<citta>TAGGIA</citta>
<indirizzo>via san Francesco, 451</indirizzo>
<cap>1018</cap>
<provincia>IM</provincia>
</progettisti>
<progettisti>
<codice>190</codice>
<cognome>MARVALDI</cognome>
<nome>LUCA</nome>
<qualifica></qualifica>
<codfiscale>MRVLCU78E02E290J</codfiscale>
<citta>SANREMO</citta>
<indirizzo>piazza ,muccioli 7</indirizzo>
<cap>18038</cap>
<provincia>IM</provincia>
</progettisti>
<progettisti>
<codice>191</codice>
<cognome>PRATTICO'</cognome>
<nome>ALESSIO</nome>
<qualifica></qualifica>
<codfiscale>PRTLSS85T23A145J</codfiscale>
<citta>TAGGIA</citta>
<indirizzo>via san Francesco, 451</indirizzo>
<cap>1018</cap>
<provincia>IM</provincia>
</progettisti>
</GEOSuedi>
